{
  "løbeId": "ae23639b-c190-465f-a366-182646d2c423",
  "responses": [
    {
      "alder": "19",
      "køn": "kvinde",
      "uddannelse": "folkeskole",
      "beskæftigelse": "dqwdw",
      "tiltalende": "1",
      "opsætning": "1",
      "billeder": "1",
      "sprog": "1",
      "farver": "1",
      "benytte": "1",
      "beskrivelse": "ddasdas",
      "stavning": "1",
      "velformuleret": "1",
      "letlæselig": "1",
      "letforståelig": "1",
      "kringlet": "1",
      "tillid": "1",
      "populær": "1"
    },
    {
      "alder": "19",
      "køn": "kvinde",
      "uddannelse": "folkeskole",
      "beskæftigelse": "dqwdw",
      "tiltalende": "1",
      "opsætning": "1",
      "billeder": "1",
      "sprog": "1",
      "farver": "1",
      "benytte": "1",
      "beskrivelse": "ddasdas",
      "stavning": "1",
      "velformuleret": "1",
      "letlæselig": "1",
      "letforståelig": "1",
      "kringlet": "1",
      "tillid": "1",
      "populær": "3"
    }
  ]
}